poetry_git_version_changer/__init__.py
zzz_poetry_git_version_changer.pth
poetry_git_version_changer-1.0.4a0.dist-info/LICENSE
poetry_git_version_changer-1.0.4a0.dist-info/WHEEL
poetry_git_version_changer-1.0.4a0.dist-info/METADATA
poetry_git_version_changer-1.0.4a0.dist-info/RECORD
